setup.cfg
setup.py
django_simple_markdown.egg-info/PKG-INFO
django_simple_markdown.egg-info/SOURCES.txt
django_simple_markdown.egg-info/dependency_links.txt
django_simple_markdown.egg-info/top_level.txt
djsmd/__init__.py
djsmd/forms.py
djsmd/widgets.py
djsmd/static/djsmd/js/simple-markdown-complete.min.js
djsmd/templates/djsmd_input.html
djsmd/templatetags/__init__.py
djsmd/templatetags/markdown_input.py