Metadata-Version: 1.1
Name: django-simple-markdown
Version: 1.0.3
Summary: Django package for markdown editing within forms. Uses simple-markdown.js
Home-page: https://github.com/Valbrand/django-simple-markdown
Author: Daniel Oliveira
Author-email: daniel@dvalbrand.com
License: UNKNOWN
Platform: UNKNOWN
Requires: Markdown
